amojo/__init__.py
amojo/main.py
amojo-0.1.0.dist-info/LICENSE
amojo-0.1.0.dist-info/METADATA
amojo-0.1.0.dist-info/WHEEL
amojo-0.1.0.dist-info/RECORD
