Metadata-Version: 2.1
Name: amojo
Version: 0.1.0
Summary: Another amoCRM API wrapper for Python
License: MIT
Author: Maksim Abramov
Author-email: 62175286+maskyy@users.noreply.github.com
Requires-Python: >=3.9,<4.0
Classifier: License :: OSI Approved :: MIT License
Classifier: Programming Language :: Python :: 3
Classifier: Programming Language :: Python :: 3.9
Classifier: Programming Language :: Python :: 3.10
Classifier: Programming Language :: Python :: 3.11
Classifier: Programming Language :: Python :: 3.12
Requires-Dist: aiohttp (>=3.10.2,<4.0.0)
